missing/__init__.py
missing/missing.py
missing_python_souravdlboy-1.1.dist-info/LICENSE
missing_python_souravdlboy-1.1.dist-info/METADATA
missing_python_souravdlboy-1.1.dist-info/WHEEL
missing_python_souravdlboy-1.1.dist-info/top_level.txt
missing_python_souravdlboy-1.1.dist-info/RECORD
