Metadata-Version: 2.1
Name: missing-python-souravdlboy
Version: 1.1
Summary: Python package for Detecting and Handling missing values with Visualizations
Home-page: https://github.com/souravs17031999/handle-missing-values
Author: sourav kumar
Author-email: sauravkumarsct@gmail.com
License: UNKNOWN
Platform: UNKNOWN
Classifier: Programming Language :: Python :: 3
Classifier: Programming Language :: Python :: 3.2
Classifier: Programming Language :: Python :: 3.3
Classifier: Programming Language :: Python :: 3.4
Classifier: Programming Language :: Python :: 3.5
Classifier: Programming Language :: Python :: 3.6
Classifier: Programming Language :: Python :: 3.7
Classifier: License :: OSI Approved :: MIT License
Classifier: Operating System :: OS Independent
Requires-Python: >=3.0
